zhTW2Num/__init__.py
zhTW2Num/lib.py
zhTW2Num-1.0.1.dist-info/LICENSE
zhTW2Num-1.0.1.dist-info/METADATA
zhTW2Num-1.0.1.dist-info/WHEEL
zhTW2Num-1.0.1.dist-info/top_level.txt
zhTW2Num-1.0.1.dist-info/RECORD
