Metadata-Version: 2.1
Name: zhTW2Num
Version: 1.0.1
Summary: Convert zh-TW numbers to Arabic numerals
Home-page: https://github.com/ben60523/zhTW2Num
Author: ben60523
Classifier: Programming Language :: Python :: 3
Classifier: License :: OSI Approved :: MIT License
Classifier: Operating System :: OS Independent
Requires-Python: >=3.6
License-File: LICENSE
